BBCHeadlines/__init__.py
BBCHeadlines-4.1.dist-info/LICENSE
BBCHeadlines-4.1.dist-info/METADATA
BBCHeadlines-4.1.dist-info/WHEEL
BBCHeadlines-4.1.dist-info/top_level.txt
BBCHeadlines-4.1.dist-info/RECORD
