Metadata-Version: 2.1
Name: BBCHeadlines
Version: 4.1
Summary: A python package to get news from BBC.
Home-page: https://github.com/gadhagod/BBCHeadlines
Author: Aarav Borthakur
Author-email: gadhaguy13@gmail.com
License: UNKNOWN
Platform: UNKNOWN
Classifier: Programming Language :: Python :: 3
Classifier: License :: OSI Approved :: MIT License
Classifier: Operating System :: OS Independent
Requires-Python: >=3.6
Requires-Dist: feedparser
